ragulate_bio/__init__.py
ragulate_bio/cli.py
ragulate_bio-0.1.1.dist-info/licenses/LICENSE
ragulate_bio-0.1.1.dist-info/METADATA
ragulate_bio-0.1.1.dist-info/WHEEL
ragulate_bio-0.1.1.dist-info/entry_points.txt
ragulate_bio-0.1.1.dist-info/top_level.txt
ragulate_bio-0.1.1.dist-info/RECORD
