Metadata-Version: 2.4
Name: ragulate-bio
Version: 0.1.1
Summary: Retrieval augmented validation for TF inference in single cell biology
Author: Mehrdad Zandigohar
License: MIT
Keywords: single-cell,regulatory networks,RAG,bioinformatics
Classifier: Programming Language :: Python :: 3
Classifier: License :: OSI Approved :: MIT License
Classifier: Intended Audience :: Science/Research
Classifier: Topic :: Scientific/Engineering :: Bio-Informatics
Requires-Python: >=3.9
License-File: LICENSE
Requires-Dist: numpy>=1.23
Dynamic: license-file
